src/data/__init__.py
src/data/gamut_data.txt
src/modules/__init__.py
src/modules/data_loader.py
src/modules/gamutmaxchroma.py
src/modules/oklchcsspalette.py
oklchcsspalette-1.2.3.dist-info/LICENSE
oklchcsspalette-1.2.3.dist-info/METADATA
oklchcsspalette-1.2.3.dist-info/WHEEL
oklchcsspalette-1.2.3.dist-info/RECORD
