Metadata-Version: 2.1
Name: oklchcsspalette
Version: 1.2.3
Summary: OKLCH color palette builder written in Python.
Home-page: https://github.com/CHRIBUR0309
License: MIT
Author: CHRIBUR_
Author-email: chribur0309@gmail.com
Requires-Python: >=3.9
Classifier: Development Status :: 5 - Production/Stable
Classifier: License :: OSI Approved :: MIT License
Classifier: Programming Language :: Python :: 3
Classifier: Programming Language :: Python :: 3.9
Classifier: Programming Language :: Python :: 3.10
Classifier: Programming Language :: Python :: 3.11
Classifier: Programming Language :: Python :: 3 :: Only
Classifier: Programming Language :: Python :: 3.12
Project-URL: Repository, https://github.com/CHRIBUR0309/OKLCH_CSS_Palette_Builder
